architxt/__init__.py
architxt/__main__.py
architxt/bucket/__init__.py
architxt/bucket/zodb.py
architxt/cli/__init__.py
architxt/cli/export.py
architxt/cli/loader.py
architxt/cli/utils.py
architxt/database/__init__.py
architxt/database/export/__init__.py
architxt/database/export/cypher.py
architxt/database/export/sql.py
architxt/database/loader/__init__.py
architxt/database/loader/cypher.py
architxt/database/loader/documents.py
architxt/database/loader/sql.py
architxt/forest.py
architxt/generator/__init__.py
architxt/grammar/__init__.py
architxt/grammar/metagrammar.interp
architxt/grammar/metagrammar.tokens
architxt/grammar/metagrammarLexer.interp
architxt/grammar/metagrammarLexer.py
architxt/grammar/metagrammarLexer.tokens
architxt/grammar/metagrammarListener.py
architxt/grammar/metagrammarParser.py
architxt/inspector.py
architxt/metrics.py
architxt/nlp/__init__.py
architxt/nlp/brat.py
architxt/nlp/entity_extractor.py
architxt/nlp/entity_resolver.py
architxt/nlp/model.py
architxt/nlp/parser/__init__.py
architxt/nlp/parser/benepar.py
architxt/nlp/parser/corenlp.py
architxt/nlp/utils.py
architxt/py.typed
architxt/schema.py
architxt/similarity.py
architxt/simplification/__init__.py
architxt/simplification/llm.py
architxt/simplification/simple_rewrite.py
architxt/simplification/tree_rewriting/__init__.py
architxt/simplification/tree_rewriting/operations/__init__.py
architxt/simplification/tree_rewriting/operations/collections.py
architxt/simplification/tree_rewriting/operations/groups.py
architxt/simplification/tree_rewriting/operations/operation.py
architxt/simplification/tree_rewriting/operations/reductions.py
architxt/simplification/tree_rewriting/operations/relations.py
architxt/tree.py
architxt/ui/__init__.py
architxt/utils.py
architxt-0.5.2.dist-info/METADATA
architxt-0.5.2.dist-info/WHEEL
architxt-0.5.2.dist-info/entry_points.txt
architxt-0.5.2.dist-info/licenses/LICENSE
architxt-0.5.2.dist-info/RECORD
