Metadata-Version: 2.4
Name: architxt
Version: 0.5.2
Summary: ArchiTXT is a tool for structuring textual data into a valid database model. It is guided by a meta-grammar and uses an iterative process of tree rewriting.
License-Expression: GPL-3.0-only
License-File: LICENSE
Keywords: python,nlp,database,structuration,text mining,text analysis,data analysis
Author: Jacques Chabin
Author-email: jacques.chabin@univ-orleans.fr
Maintainer: Nicolas Hiot
Maintainer-email: nicolas.hiot@univ-orleans.fr
Requires-Python: >=3.10,<3.13
Classifier: Development Status :: 3 - Alpha
Classifier: Environment :: Console
Classifier: Environment :: Web Environment
Classifier: Intended Audience :: Developers
Classifier: Intended Audience :: Information Technology
Classifier: Intended Audience :: Science/Research
Classifier: Natural Language :: English
Classifier: Operating System :: OS Independent
Classifier: Programming Language :: Python :: 3
Classifier: Programming Language :: Python :: 3.10
Classifier: Programming Language :: Python :: 3.11
Classifier: Programming Language :: Python :: 3.12
Classifier: Topic :: Database
Classifier: Topic :: Scientific/Engineering
Classifier: Topic :: Scientific/Engineering :: Information Analysis
Classifier: Typing :: Typed
Provides-Extra: flair
Provides-Extra: llm
Provides-Extra: ui
Requires-Dist: aiostream (>=0.7,<0.8)
Requires-Dist: antlr4-python3-runtime (>=4.13,<5)
Requires-Dist: anyio (>=4.9.0,<5.0.0)
Requires-Dist: benepar
Requires-Dist: cachetools (>=5.5.0,<6.0.0)
Requires-Dist: click (<8.4.0)
Requires-Dist: flair (>=0.15,<0.16) ; extra == "flair"
Requires-Dist: googletrans (>=4.0.2,<5.0.0)
Requires-Dist: json-repair (>=0.52,<0.53) ; extra == "llm"
Requires-Dist: langchain (>=0.3,<0.4) ; extra == "llm"
Requires-Dist: langchain-core ; extra == "llm"
Requires-Dist: langchain-huggingface ; extra == "llm"
Requires-Dist: levenshtein
Requires-Dist: mlflow (>=3.1,<3.5)
Requires-Dist: more-itertools
Requires-Dist: neo4j (>=5.28.1,<6.0.0)
Requires-Dist: nltk (>=3.9,<4.0)
Requires-Dist: numpy (>=1.16,<2.0)
Requires-Dist: pandas (>=2.3.0,<3.0.0)
Requires-Dist: platformdirs (>=4.4.0,<5.0.0)
Requires-Dist: plotly (<6.0)
Requires-Dist: pybrat (>=0.1.7,<0.2.0)
Requires-Dist: relstorage (>=4.1.1,<5.0.0)
Requires-Dist: rich (>=13.9.4,<15.0.0)
Requires-Dist: ruamel.yaml (>=0.18.0,<0.19.0)
Requires-Dist: scikit-learn (>=1.7.0,<2.0.0)
Requires-Dist: scipy (>=1.15.0,<2.0.0)
Requires-Dist: scispacy (>=0.5.5,<0.6.0)
Requires-Dist: spacy (>=3.7.0,<4.0.0)
Requires-Dist: sqlalchemy (>=2.0.39,<3.0.0)
Requires-Dist: streamlit (>=1.39.0) ; extra == "ui"
Requires-Dist: streamlit-agraph ; extra == "ui"
Requires-Dist: streamlit-tags ; extra == "ui"
Requires-Dist: toml (>=0.10.0,<0.11.0)
Requires-Dist: tqdm (>=4.60)
Requires-Dist: typer (>=0.15.1,<0.22.0)
Requires-Dist: typing-extensions
Requires-Dist: unidecode
Requires-Dist: xlrd (>=2.0.1,<3.0.0)
Requires-Dist: xmltodict (>=0.14.2,<1.1.0)
Requires-Dist: zodb (>=6.0,<7.0)
Requires-Dist: zodburi (>=3.0,<3.1)
Project-URL: Documentation, https://neplex.github.io/ArchiTXT
Project-URL: Repository, https://github.com/neplex/ArchiTXT
Project-URL: funding, https://github.com/Neplex/ArchiTXT?tab=readme-ov-file#sponsors
Project-URL: issue, https://github.com/neplex/ArchiTXT/issues
